{"v":"5.6.5","fr":60,"ip":0,"op":1350,"w":4373,"h":2460,"nm":"lipsurf layers for animation","ddd":0,"assets":[{"id":"image_0","w":229,"h":262,"u":"girl_2x/","p":"0.png","e":0},{"id":"image_1","w":233,"h":153,"u":"girl_2x/","p":"1.png","e":0},{"id":"image_2","w":221,"h":159,"u":"girl_2x/","p":"2.png","e":0},{"id":"image_3","w":335,"h":215,"u":"girl_2x/","p":"3.png","e":0},{"id":"image_4","w":706,"h":503,"u":"girl_2x/","p":"4.png","e":0},{"id":"image_5","w":359,"h":208,"u":"girl_2x/","p":"5.png","e":0},{"id":"image_6","w":536,"h":208,"u":"girl_2x/","p":"6.png","e":0},{"id":"image_7","w":919,"h":260,"u":"girl_2x/","p":"7.png","e":0},{"id":"image_8","w":530,"h":249,"u":"girl_2x/","p":"8.png","e":0},{"id":"image_9","w":361,"h":238,"u":"girl_2x/","p":"9.png","e":0},{"id":"image_10","w":361,"h":238,"u":"girl_2x/","p":"10.png","e":0},{"id":"image_11","w":361,"h":238,"u":"girl_2x/","p":"11.png","e":0},{"id":"image_12","w":530,"h":249,"u":"girl_2x/","p":"12.png","e":0},{"id":"image_13","w":530,"h":249,"u":"girl_2x/","p":"13.png","e":0},{"id":"image_14","w":530,"h":249,"u":"girl_2x/","p":"14.png","e":0},{"id":"image_15","w":99,"h":71,"u":"girl_2x/","p":"15.png","e":0},{"id":"image_16","w":123,"h":102,"u":"girl_2x/","p":"16.png","e":0},{"id":"image_17","w":1143,"h":1645,"u":"girl_2x/","p":"17.png","e":0},{"id":"image_18","w":82,"h":22,"u":"girl_2x/","p":"18.png","e":0},{"id":"image_19","w":137,"h":25,"u":"girl_2x/","p":"19.png","e":0},{"id":"image_20","w":224,"h":31,"u":"girl_2x/","p":"20.png","e":0},{"id":"image_21","w":268,"h":34,"u":"girl_2x/","p":"21.png","e":0},{"id":"image_22","w":336,"h":38,"u":"girl_2x/","p":"22.png","e":0},{"id":"image_23","w":969,"h":655,"u":"girl_2x/","p":"23.png","e":0},{"id":"image_24","w":211,"h":323,"u":"girl_2x/","p":"24.png","e":0},{"id":"image_25","w":53,"h":61,"u":"girl_2x/","p":"25.png","e":0},{"id":"image_26","w":802,"h":866,"u":"girl_2x/","p":"26.png","e":0},{"id":"image_27","w":986,"h":1116,"u":"girl_2x/","p":"27.png","e":0},{"id":"image_28","w":43,"h":45,"u":"girl_2x/","p":"28.png","e":0},{"id":"image_29","w":777,"h":353,"u":"girl_2x/","p":"29.png","e":0},{"id":"image_30","w":777,"h":342,"u":"girl_2x/","p":"30.png","e":0},{"id":"image_31","w":969,"h":655,"u":"girl_2x/","p":"31.png","e":0},{"id":"image_32","w":3900,"h":2249,"u":"girl_2x/","p":"32.png","e":0},{"id":"comp_0","layers":[{"ddd":0,"ind":1,"ty":2,"nm":"posts - long ver","refId":"image_26","sr":1,"ks":{"o":{"a":1,"k":[{"i":{"x":[0.833],"y":[0.833]},"o":{"x":[0.167],"y":[0.167]},"t":240,"s":[0]},{"i":{"x":[0.833],"y":[0.833]},"o":{"x":[0.167],"y":[0.167]},"t":249,"s":[100]},{"i":{"x":[0.833],"y":[0.833]},"o":{"x":[0.167],"y":[0.167]},"t":938,"s":[100]},{"t":949,"s":[0]}]},"p":{"a":1,"k":[{"i":{"x":0.833,"y":0.833},"o":{"x":0.167,"y":0.167},"t":338,"s":[2930.5,1638,0],"to":[0,-18.5,0],"ti":[0,18.5,0]},{"i":{"x":0.833,"y":0.833},"o":{"x":0.167,"y":0.167},"t":348,"s":[2930.5,1527,0],"to":[0,0,0],"ti":[0,0,0]},{"i":{"x":0.833,"y":0.833},"o":{"x":0.167,"y":0.167},"t":469,"s":[2930.5,1527,0],"to":[0,-20.5,0],"ti":[0,20.5,0]},{"i":{"x":0.833,"y":0.833},"o":{"x":0.167,"y":0.167},"t":479,"s":[2930.5,1404,0],"to":[0,0,0],"ti":[0,0,0]},{"i":{"x":0.833,"y":0.833},"o":{"x":0.167,"y":0.167},"t":565,"s":[2930.5,1404,0],"to":[0,-32.5,0],"ti":[0,32.5,0]},{"t":577,"s":[2930.5,1209,0]}]},"a":{"a":0,"k":[401,433,0]}},"ao":0,"ip":240,"op":986,"st":240,"bm":0},{"ddd":0,"ind":2,"ty":2,"nm":"google bg edit","refId":"image_27","sr":1,"ks":{"o":{"a":1,"k":[{"i":{"x":[0.833],"y":[0.833]},"o":{"x":[0.167],"y":[0.167]},"t":240,"s":[0]},{"i":{"x":[0.833],"y":[0.833]},"o":{"x":[0.167],"y":[0.167]},"t":249,"s":[100]},{"i":{"x":[0.833],"y":[0.833]},"o":{"x":[0.167],"y":[0.167]},"t":938,"s":[100]},{"t":949,"s":[0]}]},"p":{"a":1,"k":[{"i":{"x":0.833,"y":0.833},"o":{"x":0.167,"y":0.167},"t":338,"s":[2902.5,1598,0],"to":[0,-18.5,0],"ti":[0,18.5,0]},{"i":{"x":0.833,"y":0.833},"o":{"x":0.167,"y":0.167},"t":348,"s":[2902.5,1487,0],"to":[0,0,0],"ti":[0,0,0]},{"i":{"x":0.833,"y":0.833},"o":{"x":0.167,"y":0.167},"t":469,"s":[2902.5,1487,0],"to":[0,-20.5,0],"ti":[0,20.5,0]},{"i":{"x":0.833,"y":0.833},"o":{"x":0.167,"y":0.167},"t":479,"s":[2902.5,1364,0],"to":[0,0,0],"ti":[0,0,0]},{"i":{"x":0.833,"y":0.833},"o":{"x":0.167,"y":0.167},"t":565,"s":[2902.5,1364,0],"to":[0,-32.5,0],"ti":[0,32.5,0]},{"t":577,"s":[2902.5,1169,0]}]},"a":{"a":0,"k":[493,558,0]}},"ao":0,"ip":240,"op":986,"st":240,"bm":0}]},{"id":"comp_1","layers":[{"ddd":0,"ind":1,"ty":2,"nm":"video","refId":"image_29","sr":1,"ks":{"p":{"a":1,"k":[{"i":{"x":0.833,"y":0.833},"o":{"x":0.167,"y":0.167},"t":187,"s":[2878.5,1461.5,0],"to":[0,-35.333,0],"ti":[0,35.333,0]},{"t":224,"s":[2878.5,1249.5,0]}]},"a":{"a":0,"k":[388.5,176.5,0]}},"ao":0,"ip":142,"op":1566,"st":-489,"bm":0},{"ddd":0,"ind":2,"ty":2,"nm":"posts","refId":"image_30","sr":1,"ks":{"o":{"a":1,"k":[{"i":{"x":[0.833],"y":[0.833]},"o":{"x":[0.167],"y":[0.167]},"t":0,"s":[0]},{"i":{"x":[0.833],"y":[0.833]},"o":{"x":[0.167],"y":[0.167]},"t":14,"s":[100]},{"t":227,"s":[100]}]},"p":{"a":1,"k":[{"i":{"x":0.833,"y":0.833},"o":{"x":0.167,"y":0.167},"t":187,"s":[2878.5,1223.5,0],"to":[0,-35.333,0],"ti":[0,35.333,0]},{"t":224,"s":[2878.5,1011.5,0]}]},"a":{"a":0,"k":[388.5,171,0]}},"ao":0,"ip":0,"op":1424,"st":-631,"bm":0}]}],"layers":[{"ddd":0,"ind":1,"ty":2,"nm":"CAT 4 left mouth o 2","refId":"image_0","sr":1,"ks":{"p":{"a":0,"k":[2344,1360.5,0]},"a":{"a":0,"k":[114.5,131,0]}},"ao":0,"ip":605,"op":638,"st":605,"bm":0},{"ddd":0,"ind":2,"ty":2,"nm":"CAT 3 left mouth e","refId":"image_1","sr":1,"ks":{"p":{"a":0,"k":[2345.5,1409.5,0]},"a":{"a":0,"k":[116.5,76.5,0]}},"ao":0,"ip":224,"op":286,"st":76,"bm":0},{"ddd":0,"ind":3,"ty":2,"nm":"CAT 2 looks straight","refId":"image_2","sr":1,"ks":{"o":{"a":1,"k":[{"i":{"x":[0.833],"y":[0.833]},"o":{"x":[0.167],"y":[0.167]},"t":76,"s":[100]},{"i":{"x":[0.833],"y":[0.833]},"o":{"x":[0.167],"y":[0.167]},"t":203,"s":[100]},{"i":{"x":[0.833],"y":[0.833]},"o":{"x":[0.167],"y":[0.167]},"t":204,"s":[0]},{"i":{"x":[0.833],"y":[0.833]},"o":{"x":[0.167],"y":[0.167]},"t":285,"s":[0]},{"i":{"x":[0.833],"y":[0.833]},"o":{"x":[0.167],"y":[0.167]},"t":286,"s":[100]},{"i":{"x":[0.833],"y":[0.833]},"o":{"x":[0.167],"y":[0.167]},"t":357,"s":[100]},{"i":{"x":[0.833],"y":[0.833]},"o":{"x":[0.167],"y":[0.167]},"t":359,"s":[0]},{"i":{"x":[0.833],"y":[0.833]},"o":{"x":[0.167],"y":[0.167]},"t":469,"s":[0]},{"i":{"x":[0.833],"y":[0.833]},"o":{"x":[0.167],"y":[0.167]},"t":471,"s":[100]},{"i":{"x":[0.833],"y":[0.833]},"o":{"x":[0.167],"y":[0.167]},"t":596,"s":[100]},{"i":{"x":[0.833],"y":[0.833]},"o":{"x":[0.167],"y":[0.167]},"t":598,"s":[0]},{"i":{"x":[0.833],"y":[0.833]},"o":{"x":[0.167],"y":[0.167]},"t":637,"s":[0]},{"i":{"x":[0.833],"y":[0.833]},"o":{"x":[0.167],"y":[0.167]},"t":638,"s":[100]},{"i":{"x":[0.833],"y":[0.833]},"o":{"x":[0.167],"y":[0.167]},"t":817,"s":[100]},{"i":{"x":[0.833],"y":[0.833]},"o":{"x":[0.167],"y":[0.167]},"t":818,"s":[0]},{"i":{"x":[0.833],"y":[0.833]},"o":{"x":[0.167],"y":[0.167]},"t":961,"s":[0]},{"t":962,"s":[100]}]},"p":{"a":0,"k":[2339.5,1411.5,0]},"a":{"a":0,"k":[110.5,79.5,0]}},"ao":0,"ip":0,"op":1288,"st":76,"bm":0},{"ddd":0,"ind":4,"ty":2,"nm":"tail","refId":"image_3","sr":1,"ks":{"r":{"a":1,"k":[{"i":{"x":[0.833],"y":[0.833]},"o":{"x":[0.167],"y":[0.167]},"t":352,"s":[0]},{"i":{"x":[0.833],"y":[0.833]},"o":{"x":[0.167],"y":[0.167]},"t":376,"s":[-21]},{"i":{"x":[0.833],"y":[0.833]},"o":{"x":[0.167],"y":[0.167]},"t":392,"s":[0]},{"i":{"x":[0.833],"y":[0.833]},"o":{"x":[0.167],"y":[0.167]},"t":717,"s":[0]},{"i":{"x":[0.833],"y":[0.833]},"o":{"x":[0.167],"y":[0.167]},"t":747,"s":[-20.6]},{"t":763,"s":[0]}]},"p":{"a":1,"k":[{"i":{"x":0.833,"y":0.833},"o":{"x":0.167,"y":0.167},"t":352,"s":[2701.5,1599.5,0],"to":[7.234,6.605,0],"ti":[-9.545,-8.715,0]},{"i":{"x":0.833,"y":0.833},"o":{"x":0.167,"y":0.167},"t":376,"s":[2747.991,1638.122,0],"to":[0.571,0.521,0],"ti":[7.667,0,0]},{"i":{"x":0.833,"y":0.833},"o":{"x":0.167,"y":0.167},"t":392,"s":[2701.5,1599.5,0],"to":[-7.667,0,0],"ti":[0,0,0]},{"i":{"x":0.833,"y":0.833},"o":{"x":0.167,"y":0.167},"t":717,"s":[2701.5,1599.5,0],"to":[0,0,0],"ti":[0,0,0]},{"i":{"x":0.833,"y":0.833},"o":{"x":0.167,"y":0.167},"t":747,"s":[2747.5,1639.5,0],"to":[0,0,0],"ti":[0,0,0]},{"t":763,"s":[2701.5,1599.5,0]}]},"a":{"a":0,"k":[167.5,107.5,0]}},"ao":0,"ip":0,"op":1350,"st":76,"bm":0},{"ddd":0,"ind":5,"ty":2,"nm":"CAT 1 without a tail","refId":"image_4","sr":1,"ks":{"p":{"a":0,"k":[2553,1480.5,0]},"a":{"a":0,"k":[353,251.5,0]}},"ao":0,"ip":0,"op":1350,"st":76,"bm":0},{"ddd":0,"ind":6,"ty":2,"nm":"bubble cat 1 txt","refId":"image_5","sr":1,"ks":{"o":{"a":1,"k":[{"i":{"x":[0.833],"y":[0.833]},"o":{"x":[0.167],"y":[0.167]},"t":225,"s":[0]},{"i":{"x":[0.833],"y":[0.833]},"o":{"x":[0.167],"y":[0.167]},"t":235,"s":[100]},{"i":{"x":[0.833],"y":[0.833]},"o":{"x":[0.167],"y":[0.167]},"t":290,"s":[100]},{"t":300,"s":[0]}]},"p":{"a":1,"k":[{"i":{"x":0.833,"y":0.833},"o":{"x":0.167,"y":0.167},"t":225,"s":[2443.5,1723,0],"to":[0,16.333,0],"ti":[0,-16.333,0]},{"i":{"x":0.833,"y":0.833},"o":{"x":0.167,"y":0.167},"t":235,"s":[2443.5,1821,0],"to":[0,0,0],"ti":[0,0,0]},{"i":{"x":0.833,"y":0.833},"o":{"x":0.167,"y":0.167},"t":290,"s":[2443.5,1821,0],"to":[0,15,0],"ti":[0,-15,0]},{"t":300,"s":[2443.5,1911,0]}]},"a":{"a":0,"k":[179.5,104,0]}},"ao":0,"ip":225,"op":300,"st":195,"bm":0},{"ddd":0,"ind":7,"ty":2,"nm":"bubble cat 2 txt","refId":"image_6","sr":1,"ks":{"o":{"a":1,"k":[{"i":{"x":[0.833],"y":[0.833]},"o":{"x":[0.167],"y":[0.167]},"t":604,"s":[0]},{"i":{"x":[0.833],"y":[0.833]},"o":{"x":[0.167],"y":[0.167]},"t":614,"s":[100]},{"i":{"x":[0.833],"y":[0.833]},"o":{"x":[0.167],"y":[0.167]},"t":666,"s":[100]},{"t":676,"s":[0]}]},"p":{"a":1,"k":[{"i":{"x":0.833,"y":0.833},"o":{"x":0.167,"y":0.167},"t":604,"s":[2555,1743.5,0],"to":[0,16.333,0],"ti":[0,-16.333,0]},{"i":{"x":0.833,"y":0.833},"o":{"x":0.167,"y":0.167},"t":614,"s":[2555,1841.5,0],"to":[0,0,0],"ti":[0,0,0]},{"i":{"x":0.833,"y":0.833},"o":{"x":0.167,"y":0.167},"t":666,"s":[2555,1841.5,0],"to":[0,15,0],"ti":[0,-15,0]},{"t":676,"s":[2555,1931.5,0]}]},"a":{"a":0,"k":[268,104,0]}},"ao":0,"ip":604,"op":676,"st":574,"bm":0},{"ddd":0,"ind":8,"ty":2,"nm":"bubble 1 girl txt","refId":"image_7","sr":1,"ks":{"o":{"a":1,"k":[{"i":{"x":[0.833],"y":[0.833]},"o":{"x":[0.167],"y":[0.167]},"t":68,"s":[0]},{"i":{"x":[0.833],"y":[0.833]},"o":{"x":[0.167],"y":[0.167]},"t":78,"s":[100]},{"i":{"x":[0.833],"y":[0.833]},"o":{"x":[0.167],"y":[0.167]},"t":215,"s":[100]},{"t":225,"s":[0]}]},"p":{"a":1,"k":[{"i":{"x":0.833,"y":0.833},"o":{"x":0.167,"y":0.167},"t":68,"s":[2205.5,997,0],"to":[0,-20.667,0],"ti":[0,20.667,0]},{"i":{"x":0.833,"y":0.833},"o":{"x":0.167,"y":0.167},"t":78,"s":[2205.5,873,0],"to":[0,0,0],"ti":[0,0,0]},{"i":{"x":0.833,"y":0.833},"o":{"x":0.167,"y":0.167},"t":215,"s":[2205.5,873,0],"to":[0,-23.333,0],"ti":[0,23.333,0]},{"t":225,"s":[2205.5,733,0]}]},"a":{"a":0,"k":[459.5,130,0]}},"ao":0,"ip":68,"op":226,"st":106,"bm":0},{"ddd":0,"ind":9,"ty":2,"nm":"bubble 2 girl txt","refId":"image_8","sr":1,"ks":{"o":{"a":1,"k":[{"i":{"x":[0.833],"y":[0.833]},"o":{"x":[0.167],"y":[0.167]},"t":285,"s":[0]},{"i":{"x":[0.833],"y":[0.833]},"o":{"x":[0.167],"y":[0.167]},"t":295,"s":[100]},{"i":{"x":[0.833],"y":[0.833]},"o":{"x":[0.167],"y":[0.167]},"t":364,"s":[100]},{"t":374,"s":[0]}]},"p":{"a":1,"k":[{"i":{"x":0.833,"y":0.833},"o":{"x":0.167,"y":0.167},"t":285,"s":[2013,1002.5,0],"to":[0,-20.667,0],"ti":[0,20.667,0]},{"i":{"x":0.833,"y":0.833},"o":{"x":0.167,"y":0.167},"t":295,"s":[2013,878.5,0],"to":[0,0,0],"ti":[0,0,0]},{"i":{"x":0.833,"y":0.833},"o":{"x":0.167,"y":0.167},"t":364,"s":[2013,878.5,0],"to":[0,-23.333,0],"ti":[0,23.333,0]},{"t":374,"s":[2013,738.5,0]}]},"a":{"a":0,"k":[265,124.5,0]}},"ao":0,"ip":285,"op":375,"st":285,"bm":0},{"ddd":0,"ind":10,"ty":2,"nm":"bubble 3 girl txt 2","refId":"image_9","sr":1,"ks":{"o":{"a":1,"k":[{"i":{"x":[0.833],"y":[0.833]},"o":{"x":[0.167],"y":[0.167]},"t":406,"s":[0]},{"i":{"x":[0.833],"y":[0.833]},"o":{"x":[0.167],"y":[0.167]},"t":416,"s":[100]},{"i":{"x":[0.833],"y":[0.833]},"o":{"x":[0.167],"y":[0.167]},"t":465,"s":[100]},{"t":475,"s":[0]}]},"p":{"a":1,"k":[{"i":{"x":0.833,"y":0.833},"o":{"x":0.167,"y":0.167},"t":406,"s":[1906.5,1007,0],"to":[0,-20.667,0],"ti":[0,20.667,0]},{"i":{"x":0.833,"y":0.833},"o":{"x":0.167,"y":0.167},"t":416,"s":[1906.5,883,0],"to":[0,0,0],"ti":[0,0,0]},{"i":{"x":0.833,"y":0.833},"o":{"x":0.167,"y":0.167},"t":465,"s":[1906.5,883,0],"to":[0,-23.333,0],"ti":[0,23.333,0]},{"t":475,"s":[1906.5,743,0]}]},"a":{"a":0,"k":[180.5,119,0]}},"ao":0,"ip":406,"op":476,"st":406,"bm":0},{"ddd":0,"ind":11,"ty":2,"nm":"bubble 3 girl txt","refId":"image_9","sr":1,"ks":{"o":{"a":1,"k":[{"i":{"x":[0.833],"y":[0.833]},"o":{"x":[0.167],"y":[0.167]},"t":500,"s":[0]},{"i":{"x":[0.833],"y":[0.833]},"o":{"x":[0.167],"y":[0.167]},"t":510,"s":[100]},{"i":{"x":[0.833],"y":[0.833]},"o":{"x":[0.167],"y":[0.167]},"t":565,"s":[100]},{"t":575,"s":[0]}]},"p":{"a":1,"k":[{"i":{"x":0.833,"y":0.833},"o":{"x":0.167,"y":0.167},"t":500,"s":[1906.5,1007,0],"to":[0,-20.667,0],"ti":[0,20.667,0]},{"i":{"x":0.833,"y":0.833},"o":{"x":0.167,"y":0.167},"t":510,"s":[1906.5,883,0],"to":[0,0,0],"ti":[0,0,0]},{"i":{"x":0.833,"y":0.833},"o":{"x":0.167,"y":0.167},"t":565,"s":[1906.5,883,0],"to":[0,-23.333,0],"ti":[0,23.333,0]},{"t":575,"s":[1906.5,743,0]}]},"a":{"a":0,"k":[180.5,119,0]}},"ao":0,"ip":500,"op":576,"st":500,"bm":0},{"ddd":0,"ind":12,"ty":2,"nm":"bubble 4 girl txt","refId":"image_10","sr":1,"ks":{"o":{"a":1,"k":[{"i":{"x":[0.833],"y":[0.833]},"o":{"x":[0.167],"y":[0.167]},"t":614,"s":[0]},{"i":{"x":[0.833],"y":[0.833]},"o":{"x":[0.167],"y":[0.167]},"t":624,"s":[100]},{"i":{"x":[0.833],"y":[0.833]},"o":{"x":[0.167],"y":[0.167]},"t":679,"s":[100]},{"t":689,"s":[0]}]},"p":{"a":1,"k":[{"i":{"x":0.833,"y":0.833},"o":{"x":0.167,"y":0.167},"t":614,"s":[1906.5,1007,0],"to":[0,-20.667,0],"ti":[0,20.667,0]},{"i":{"x":0.833,"y":0.833},"o":{"x":0.167,"y":0.167},"t":624,"s":[1906.5,883,0],"to":[0,0,0],"ti":[0,0,0]},{"i":{"x":0.833,"y":0.833},"o":{"x":0.167,"y":0.167},"t":679,"s":[1906.5,883,0],"to":[0,-23.333,0],"ti":[0,23.333,0]},{"t":689,"s":[1906.5,743,0]}]},"a":{"a":0,"k":[180.5,119,0]}},"ao":0,"ip":614,"op":689,"st":614,"bm":0},{"ddd":0,"ind":13,"ty":2,"nm":"bubble 5 girl txt","refId":"image_11","sr":1,"ks":{"o":{"a":1,"k":[{"i":{"x":[0.833],"y":[0.833]},"o":{"x":[0.167],"y":[0.167]},"t":750,"s":[0]},{"i":{"x":[0.833],"y":[0.833]},"o":{"x":[0.167],"y":[0.167]},"t":760,"s":[100]},{"i":{"x":[0.833],"y":[0.833]},"o":{"x":[0.167],"y":[0.167]},"t":802,"s":[100]},{"t":812,"s":[0]}]},"p":{"a":1,"k":[{"i":{"x":0.833,"y":0.833},"o":{"x":0.167,"y":0.167},"t":750,"s":[1906.5,1007,0],"to":[0,-20.667,0],"ti":[0,20.667,0]},{"i":{"x":0.833,"y":0.833},"o":{"x":0.167,"y":0.167},"t":760,"s":[1906.5,883,0],"to":[0,0,0],"ti":[0,0,0]},{"i":{"x":0.833,"y":0.833},"o":{"x":0.167,"y":0.167},"t":802,"s":[1906.5,883,0],"to":[0,-23.333,0],"ti":[0,23.333,0]},{"t":812,"s":[1906.5,743,0]}]},"a":{"a":0,"k":[180.5,119,0]}},"ao":0,"ip":750,"op":813,"st":750,"bm":0},{"ddd":0,"ind":14,"ty":2,"nm":"bubble 6 girl txt","refId":"image_12","sr":1,"ks":{"o":{"a":1,"k":[{"i":{"x":[0.833],"y":[0.833]},"o":{"x":[0.167],"y":[0.167]},"t":870,"s":[0]},{"i":{"x":[0.833],"y":[0.833]},"o":{"x":[0.167],"y":[0.167]},"t":880,"s":[100]},{"i":{"x":[0.833],"y":[0.833]},"o":{"x":[0.167],"y":[0.167]},"t":947,"s":[100]},{"t":957,"s":[0]}]},"p":{"a":1,"k":[{"i":{"x":0.833,"y":0.833},"o":{"x":0.167,"y":0.167},"t":870,"s":[2013,1002.5,0],"to":[0,-20.667,0],"ti":[0,20.667,0]},{"i":{"x":0.833,"y":0.833},"o":{"x":0.167,"y":0.167},"t":880,"s":[2013,878.5,0],"to":[0,0,0],"ti":[0,0,0]},{"i":{"x":0.833,"y":0.833},"o":{"x":0.167,"y":0.167},"t":947,"s":[2013,878.5,0],"to":[0,-23.333,0],"ti":[0,23.333,0]},{"t":957,"s":[2013,738.5,0]}]},"a":{"a":0,"k":[265,124.5,0]}},"ao":0,"ip":870,"op":957,"st":870,"bm":0},{"ddd":0,"ind":15,"ty":2,"nm":"bubble 7 girl txt","refId":"image_13","sr":1,"ks":{"o":{"a":1,"k":[{"i":{"x":[0.833],"y":[0.833]},"o":{"x":[0.167],"y":[0.167]},"t":1020,"s":[0]},{"i":{"x":[0.833],"y":[0.833]},"o":{"x":[0.167],"y":[0.167]},"t":1030,"s":[100]},{"i":{"x":[0.833],"y":[0.833]},"o":{"x":[0.167],"y":[0.167]},"t":1096,"s":[100]},{"t":1106,"s":[0]}]},"p":{"a":1,"k":[{"i":{"x":0.833,"y":0.833},"o":{"x":0.167,"y":0.167},"t":1020,"s":[2013,1002.5,0],"to":[0,-20.667,0],"ti":[0,20.667,0]},{"i":{"x":0.833,"y":0.833},"o":{"x":0.167,"y":0.167},"t":1030,"s":[2013,878.5,0],"to":[0,0,0],"ti":[0,0,0]},{"i":{"x":0.833,"y":0.833},"o":{"x":0.167,"y":0.167},"t":1096,"s":[2013,878.5,0],"to":[0,-23.333,0],"ti":[0,23.333,0]},{"t":1106,"s":[2013,738.5,0]}]},"a":{"a":0,"k":[265,124.5,0]}},"ao":0,"ip":1020,"op":1106,"st":1020,"bm":0},{"ddd":0,"ind":16,"ty":2,"nm":"bubble 8 girl txt","refId":"image_14","sr":1,"ks":{"o":{"a":1,"k":[{"i":{"x":[0.833],"y":[0.833]},"o":{"x":[0.167],"y":[0.167]},"t":1191,"s":[0]},{"i":{"x":[0.833],"y":[0.833]},"o":{"x":[0.167],"y":[0.167]},"t":1201,"s":[100]},{"i":{"x":[0.833],"y":[0.833]},"o":{"x":[0.167],"y":[0.167]},"t":1271,"s":[100]},{"t":1281,"s":[0]}]},"p":{"a":1,"k":[{"i":{"x":0.833,"y":0.833},"o":{"x":0.167,"y":0.167},"t":1191,"s":[2013,1002.5,0],"to":[0,-20.667,0],"ti":[0,20.667,0]},{"i":{"x":0.833,"y":0.833},"o":{"x":0.167,"y":0.167},"t":1201,"s":[2013,878.5,0],"to":[0,0,0],"ti":[0,0,0]},{"i":{"x":0.833,"y":0.833},"o":{"x":0.167,"y":0.167},"t":1271,"s":[2013,878.5,0],"to":[0,-23.333,0],"ti":[0,23.333,0]},{"t":1281,"s":[2013,738.5,0]}]},"a":{"a":0,"k":[265,124.5,0]}},"ao":0,"ip":1191,"op":1281,"st":1191,"bm":0},{"ddd":0,"ind":17,"ty":2,"nm":"GIRL 2 mouth E","refId":"image_15","sr":1,"ks":{"o":{"a":1,"k":[{"i":{"x":[0.833],"y":[0.833]},"o":{"x":[0.167],"y":[0.167]},"t":131,"s":[0]},{"i":{"x":[0.833],"y":[0.833]},"o":{"x":[0.167],"y":[0.167]},"t":132,"s":[100]},{"i":{"x":[0.833],"y":[0.833]},"o":{"x":[0.167],"y":[0.167]},"t":143,"s":[100]},{"i":{"x":[0.833],"y":[0.833]},"o":{"x":[0.167],"y":[0.167]},"t":144,"s":[0]},{"i":{"x":[0.833],"y":[0.833]},"o":{"x":[0.167],"y":[0.167]},"t":151,"s":[0]},{"i":{"x":[0.833],"y":[0.833]},"o":{"x":[0.167],"y":[0.167]},"t":152,"s":[100]},{"i":{"x":[0.833],"y":[0.833]},"o":{"x":[0.167],"y":[0.167]},"t":161,"s":[100]},{"i":{"x":[0.833],"y":[0.833]},"o":{"x":[0.167],"y":[0.167]},"t":162,"s":[0]},{"i":{"x":[0.833],"y":[0.833]},"o":{"x":[0.167],"y":[0.167]},"t":179,"s":[0]},{"i":{"x":[0.833],"y":[0.833]},"o":{"x":[0.167],"y":[0.167]},"t":180,"s":[100]},{"i":{"x":[0.833],"y":[0.833]},"o":{"x":[0.167],"y":[0.167]},"t":189,"s":[100]},{"i":{"x":[0.833],"y":[0.833]},"o":{"x":[0.167],"y":[0.167]},"t":190,"s":[0]},{"i":{"x":[0.833],"y":[0.833]},"o":{"x":[0.167],"y":[0.167]},"t":614,"s":[0]},{"i":{"x":[0.833],"y":[0.833]},"o":{"x":[0.167],"y":[0.167]},"t":615,"s":[100]},{"i":{"x":[0.833],"y":[0.833]},"o":{"x":[0.167],"y":[0.167]},"t":639,"s":[100]},{"i":{"x":[0.833],"y":[0.833]},"o":{"x":[0.167],"y":[0.167]},"t":640,"s":[0]},{"i":{"x":[0.833],"y":[0.833]},"o":{"x":[0.167],"y":[0.167]},"t":759,"s":[0]},{"i":{"x":[0.833],"y":[0.833]},"o":{"x":[0.167],"y":[0.167]},"t":760,"s":[100]},{"i":{"x":[0.833],"y":[0.833]},"o":{"x":[0.167],"y":[0.167]},"t":770,"s":[100]},{"i":{"x":[0.833],"y":[0.833]},"o":{"x":[0.167],"y":[0.167]},"t":771,"s":[0]},{"i":{"x":[0.833],"y":[0.833]},"o":{"x":[0.167],"y":[0.167]},"t":912,"s":[0]},{"i":{"x":[0.833],"y":[0.833]},"o":{"x":[0.167],"y":[0.167]},"t":913,"s":[100]},{"i":{"x":[0.833],"y":[0.833]},"o":{"x":[0.167],"y":[0.167]},"t":930,"s":[100]},{"i":{"x":[0.833],"y":[0.833]},"o":{"x":[0.167],"y":[0.167]},"t":931,"s":[0]},{"i":{"x":[0.833],"y":[0.833]},"o":{"x":[0.167],"y":[0.167]},"t":1020,"s":[0]},{"i":{"x":[0.833],"y":[0.833]},"o":{"x":[0.167],"y":[0.167]},"t":1021,"s":[100]},{"i":{"x":[0.833],"y":[0.833]},"o":{"x":[0.167],"y":[0.167]},"t":1032,"s":[100]},{"i":{"x":[0.833],"y":[0.833]},"o":{"x":[0.167],"y":[0.167]},"t":1033,"s":[0]},{"i":{"x":[0.833],"y":[0.833]},"o":{"x":[0.167],"y":[0.167]},"t":1039,"s":[0]},{"i":{"x":[0.833],"y":[0.833]},"o":{"x":[0.167],"y":[0.167]},"t":1040,"s":[100]},{"i":{"x":[0.833],"y":[0.833]},"o":{"x":[0.167],"y":[0.167]},"t":1048,"s":[100]},{"i":{"x":[0.833],"y":[0.833]},"o":{"x":[0.167],"y":[0.167]},"t":1049,"s":[0]},{"i":{"x":[0.833],"y":[0.833]},"o":{"x":[0.167],"y":[0.167]},"t":1197,"s":[0]},{"i":{"x":[0.833],"y":[0.833]},"o":{"x":[0.167],"y":[0.167]},"t":1198,"s":[100]},{"i":{"x":[0.833],"y":[0.833]},"o":{"x":[0.167],"y":[0.167]},"t":1208,"s":[100]},{"i":{"x":[0.833],"y":[0.833]},"o":{"x":[0.167],"y":[0.167]},"t":1209,"s":[0]},{"i":{"x":[0.833],"y":[0.833]},"o":{"x":[0.167],"y":[0.167]},"t":1224,"s":[0]},{"i":{"x":[0.833],"y":[0.833]},"o":{"x":[0.167],"y":[0.167]},"t":1225,"s":[100]},{"i":{"x":[0.833],"y":[0.833]},"o":{"x":[0.167],"y":[0.167]},"t":1235,"s":[100]},{"t":1236,"s":[0]}]},"p":{"a":0,"k":[1607.5,1143.5,0]},"a":{"a":0,"k":[49.5,35.5,0]}},"ao":0,"ip":74,"op":1256,"st":153,"bm":0},{"ddd":0,"ind":18,"ty":2,"nm":"GIRL 3 mouth 0","refId":"image_16","sr":1,"ks":{"o":{"a":1,"k":[{"i":{"x":[0.833],"y":[0.833]},"o":{"x":[0.167],"y":[0.167]},"t":74,"s":[0]},{"i":{"x":[0.833],"y":[0.833]},"o":{"x":[0.167],"y":[0.167]},"t":75,"s":[100]},{"i":{"x":[0.833],"y":[0.833]},"o":{"x":[0.167],"y":[0.167]},"t":89,"s":[100]},{"i":{"x":[0.833],"y":[0.833]},"o":{"x":[0.167],"y":[0.167]},"t":90,"s":[0]},{"i":{"x":[0.833],"y":[0.833]},"o":{"x":[0.167],"y":[0.167]},"t":104,"s":[0]},{"i":{"x":[0.833],"y":[0.833]},"o":{"x":[0.167],"y":[0.167]},"t":105,"s":[100]},{"i":{"x":[0.833],"y":[0.833]},"o":{"x":[0.167],"y":[0.167]},"t":115,"s":[100]},{"i":{"x":[0.833],"y":[0.833]},"o":{"x":[0.167],"y":[0.167]},"t":116,"s":[0]},{"i":{"x":[0.833],"y":[0.833]},"o":{"x":[0.167],"y":[0.167]},"t":169,"s":[0]},{"i":{"x":[0.833],"y":[0.833]},"o":{"x":[0.167],"y":[0.167]},"t":170,"s":[100]},{"i":{"x":[0.833],"y":[0.833]},"o":{"x":[0.167],"y":[0.167]},"t":177,"s":[100]},{"i":{"x":[0.833],"y":[0.833]},"o":{"x":[0.167],"y":[0.167]},"t":178,"s":[0]},{"i":{"x":[0.833],"y":[0.833]},"o":{"x":[0.167],"y":[0.167]},"t":194,"s":[0]},{"i":{"x":[0.833],"y":[0.833]},"o":{"x":[0.167],"y":[0.167]},"t":195,"s":[100]},{"i":{"x":[0.833],"y":[0.833]},"o":{"x":[0.167],"y":[0.167]},"t":204,"s":[100]},{"i":{"x":[0.833],"y":[0.833]},"o":{"x":[0.167],"y":[0.167]},"t":205,"s":[0]},{"i":{"x":[0.833],"y":[0.833]},"o":{"x":[0.167],"y":[0.167]},"t":292,"s":[0]},{"i":{"x":[0.833],"y":[0.833]},"o":{"x":[0.167],"y":[0.167]},"t":293,"s":[100]},{"i":{"x":[0.833],"y":[0.833]},"o":{"x":[0.167],"y":[0.167]},"t":303,"s":[100]},{"i":{"x":[0.833],"y":[0.833]},"o":{"x":[0.167],"y":[0.167]},"t":304,"s":[0]},{"i":{"x":[0.833],"y":[0.833]},"o":{"x":[0.167],"y":[0.167]},"t":310,"s":[0]},{"i":{"x":[0.833],"y":[0.833]},"o":{"x":[0.167],"y":[0.167]},"t":311,"s":[100]},{"i":{"x":[0.833],"y":[0.833]},"o":{"x":[0.167],"y":[0.167]},"t":321,"s":[100]},{"i":{"x":[0.833],"y":[0.833]},"o":{"x":[0.167],"y":[0.167]},"t":322,"s":[0]},{"i":{"x":[0.833],"y":[0.833]},"o":{"x":[0.167],"y":[0.167]},"t":415,"s":[0]},{"i":{"x":[0.833],"y":[0.833]},"o":{"x":[0.167],"y":[0.167]},"t":416,"s":[100]},{"i":{"x":[0.833],"y":[0.833]},"o":{"x":[0.167],"y":[0.167]},"t":434,"s":[100]},{"i":{"x":[0.833],"y":[0.833]},"o":{"x":[0.167],"y":[0.167]},"t":435,"s":[0]},{"i":{"x":[0.833],"y":[0.833]},"o":{"x":[0.167],"y":[0.167]},"t":507,"s":[0]},{"i":{"x":[0.833],"y":[0.833]},"o":{"x":[0.167],"y":[0.167]},"t":508,"s":[100]},{"i":{"x":[0.833],"y":[0.833]},"o":{"x":[0.167],"y":[0.167]},"t":526,"s":[100]},{"i":{"x":[0.833],"y":[0.833]},"o":{"x":[0.167],"y":[0.167]},"t":527,"s":[0]},{"i":{"x":[0.833],"y":[0.833]},"o":{"x":[0.167],"y":[0.167]},"t":780,"s":[0]},{"i":{"x":[0.833],"y":[0.833]},"o":{"x":[0.167],"y":[0.167]},"t":781,"s":[100]},{"i":{"x":[0.833],"y":[0.833]},"o":{"x":[0.167],"y":[0.167]},"t":791,"s":[100]},{"i":{"x":[0.833],"y":[0.833]},"o":{"x":[0.167],"y":[0.167]},"t":792,"s":[0]},{"i":{"x":[0.833],"y":[0.833]},"o":{"x":[0.167],"y":[0.167]},"t":879,"s":[0]},{"i":{"x":[0.833],"y":[0.833]},"o":{"x":[0.167],"y":[0.167]},"t":880,"s":[100]},{"i":{"x":[0.833],"y":[0.833]},"o":{"x":[0.167],"y":[0.167]},"t":893,"s":[100]},{"i":{"x":[0.833],"y":[0.833]},"o":{"x":[0.167],"y":[0.167]},"t":894,"s":[0]},{"i":{"x":[0.833],"y":[0.833]},"o":{"x":[0.167],"y":[0.167]},"t":1058,"s":[0]},{"i":{"x":[0.833],"y":[0.833]},"o":{"x":[0.167],"y":[0.167]},"t":1059,"s":[100]},{"i":{"x":[0.833],"y":[0.833]},"o":{"x":[0.167],"y":[0.167]},"t":1068,"s":[100]},{"i":{"x":[0.833],"y":[0.833]},"o":{"x":[0.167],"y":[0.167]},"t":1069,"s":[0]},{"i":{"x":[0.833],"y":[0.833]},"o":{"x":[0.167],"y":[0.167]},"t":1241,"s":[0]},{"i":{"x":[0.833],"y":[0.833]},"o":{"x":[0.167],"y":[0.167]},"t":1242,"s":[100]},{"i":{"x":[0.833],"y":[0.833]},"o":{"x":[0.167],"y":[0.167]},"t":1255,"s":[100]},{"t":1256,"s":[0]}]},"p":{"a":0,"k":[1597.5,1141.5,0]},"a":{"a":0,"k":[61.5,51,0]}},"ao":0,"ip":34,"op":1257,"st":148,"bm":0},{"ddd":0,"ind":19,"ty":2,"nm":"GIRL 1 closed mouth","refId":"image_17","sr":1,"ks":{"p":{"a":0,"k":[1757.5,1571.5,0]},"a":{"a":0,"k":[571.5,822.5,0]}},"ao":0,"ip":-10,"op":1350,"st":76,"bm":0},{"ddd":0,"ind":20,"ty":2,"nm":"words 1","refId":"image_18","sr":1,"ks":{"p":{"a":0,"k":[2721,1095,0]},"a":{"a":0,"k":[41,11,0]}},"ao":0,"ip":79,"op":105,"st":82,"bm":0},{"ddd":0,"ind":21,"ty":2,"nm":"words 2","refId":"image_19","sr":1,"ks":{"p":{"a":0,"k":[2748.5,1096.5,0]},"a":{"a":0,"k":[68.5,12.5,0]}},"ao":0,"ip":105,"op":131,"st":108,"bm":0},{"ddd":0,"ind":22,"ty":2,"nm":"words 3","refId":"image_20","sr":1,"ks":{"p":{"a":0,"k":[2792,1099.5,0]},"a":{"a":0,"k":[112,15.5,0]}},"ao":0,"ip":131,"op":157,"st":134,"bm":0},{"ddd":0,"ind":23,"ty":2,"nm":"words 4","refId":"image_21","sr":1,"ks":{"p":{"a":0,"k":[2814,1101,0]},"a":{"a":0,"k":[134,17,0]}},"ao":0,"ip":157,"op":183,"st":160,"bm":0},{"ddd":0,"ind":24,"ty":2,"nm":"words 5","refId":"image_22","sr":1,"ks":{"o":{"a":1,"k":[{"i":{"x":[0.833],"y":[0.833]},"o":{"x":[0.167],"y":[0.167]},"t":203,"s":[100]},{"t":221,"s":[0]}]},"p":{"a":0,"k":[2848,1103,0]},"a":{"a":0,"k":[168,19,0]}},"ao":0,"ip":183,"op":222,"st":181,"bm":0},{"ddd":0,"ind":25,"ty":2,"nm":"bg google","refId":"image_23","sr":1,"ks":{"o":{"a":1,"k":[{"i":{"x":[0.833],"y":[0.833]},"o":{"x":[0.167],"y":[0.167]},"t":30,"s":[0]},{"i":{"x":[0.833],"y":[0.833]},"o":{"x":[0.167],"y":[0.167]},"t":42,"s":[100]},{"i":{"x":[0.833],"y":[0.833]},"o":{"x":[0.167],"y":[0.167]},"t":220,"s":[100]},{"t":238,"s":[0]}]},"p":{"a":0,"k":[2906.5,1083.5,0]},"a":{"a":0,"k":[484.5,327.5,0]}},"ao":0,"ip":0,"op":239,"st":76,"bm":0},{"ddd":0,"ind":26,"ty":2,"nm":"annotation","refId":"image_24","sr":1,"ks":{"o":{"a":1,"k":[{"i":{"x":[0.833],"y":[0.833]},"o":{"x":[0.167],"y":[0.167]},"t":942,"s":[100]},{"t":947,"s":[0]}]},"p":{"a":0,"k":[2829.5,1078.5,0]},"a":{"a":0,"k":[105.5,161.5,0]}},"ao":0,"ef":[{"ty":31,"nm":"Mesh Warp","np":6,"mn":"ADBE MESH WARP","ix":1,"en":1,"ef":[{"ty":0,"nm":"Rows","mn":"ADBE MESH WARP-0001","ix":1,"v":{"a":0,"k":7}},{"ty":0,"nm":"Columns","mn":"ADBE MESH WARP-0002","ix":2,"v":{"a":0,"k":7}},{"ty":0,"nm":"Quality","mn":"ADBE MESH WARP-0005","ix":3,"v":{"a":0,"k":8}},{}]}],"ip":651,"op":947,"st":835,"bm":0},{"ddd":0,"ind":27,"ty":2,"nm":"annotation z1/lipsurf layers for animation.psd 2","cl":"psd","refId":"image_25","sr":1,"ks":{"o":{"a":1,"k":[{"i":{"x":[0.833],"y":[0.833]},"o":{"x":[0.167],"y":[0.167]},"t":799,"s":[100]},{"i":{"x":[0.833],"y":[0.833]},"o":{"x":[0.167],"y":[0.167]},"t":805,"s":[100]},{"i":{"x":[0.833],"y":[0.833]},"o":{"x":[0.167],"y":[0.167]},"t":806,"s":[0]},{"i":{"x":[0.833],"y":[0.833]},"o":{"x":[0.167],"y":[0.167]},"t":812,"s":[0]},{"i":{"x":[0.833],"y":[0.833]},"o":{"x":[0.167],"y":[0.167]},"t":813,"s":[100]},{"i":{"x":[0.833],"y":[0.833]},"o":{"x":[0.167],"y":[0.167]},"t":819,"s":[100]},{"i":{"x":[0.833],"y":[0.833]},"o":{"x":[0.167],"y":[0.167]},"t":820,"s":[0]},{"i":{"x":[0.833],"y":[0.833]},"o":{"x":[0.167],"y":[0.167]},"t":826,"s":[0]},{"i":{"x":[0.833],"y":[0.833]},"o":{"x":[0.167],"y":[0.167]},"t":827,"s":[100]},{"i":{"x":[0.833],"y":[0.833]},"o":{"x":[0.167],"y":[0.167]},"t":942,"s":[100]},{"t":947,"s":[0]}]},"p":{"a":0,"k":[2746.5,925,0]},"a":{"a":0,"k":[26.5,30.5,0]},"s":{"a":0,"k":[92.453,92.453,100]}},"ao":0,"ip":799,"op":947,"st":277,"bm":0},{"ddd":0,"ind":28,"ty":0,"nm":"screen google search","refId":"comp_0","sr":1,"ks":{"p":{"a":0,"k":[2186.5,1230,0]},"a":{"a":0,"k":[2186.5,1524.5,0]}},"ao":0,"hasMask":true,"masksProperties":[{"inv":false,"mode":"a","pt":{"a":0,"k":{"i":[[0,0],[0,0],[0,0],[0,0]],"o":[[0,0],[0,0],[0,0],[0,0]],"v":[[3375.969,1070],[2450.5,1054],[2422.5,1573.063],[3351.969,1689.063]],"c":true}},"o":{"a":0,"k":100},"x":{"a":0,"k":0},"nm":"Mask 1"}],"ef":[{"ty":5,"nm":"Corner Pin","np":6,"mn":"ADBE Corner Pin","ix":1,"en":1,"ef":[{"ty":3,"nm":"Upper Left","mn":"ADBE Corner Pin-0001","ix":1,"v":{"a":0,"k":[0,0]}},{"ty":3,"nm":"Upper Right","mn":"ADBE Corner Pin-0002","ix":2,"v":{"a":0,"k":[4373,0]}},{"ty":3,"nm":"Lower Left","mn":"ADBE Corner Pin-0003","ix":3,"v":{"a":0,"k":[0,3049]}},{"ty":3,"nm":"Lower Right","mn":"ADBE Corner Pin-0004","ix":4,"v":{"a":0,"k":[4373,3049]}}]}],"w":4373,"h":3049,"ip":239,"op":948,"st":-1,"bm":0},{"ddd":0,"ind":29,"ty":2,"nm":"video button","refId":"image_28","sr":1,"ks":{"p":{"a":1,"k":[{"i":{"x":0.833,"y":0.833},"o":{"x":0.167,"y":0.167},"t":1151,"s":[2757.5,1278.5,0],"to":[0,-20.5,0],"ti":[0,20.5,0]},{"t":1176,"s":[2757.5,1155.5,0]}]},"a":{"a":0,"k":[21.5,22.5,0]}},"ao":0,"ip":1151,"op":1269,"st":1120,"bm":0},{"ddd":0,"ind":30,"ty":1,"nm":"throbber 4","sr":1,"ks":{"r":{"a":1,"k":[{"i":{"x":[0.833],"y":[0.833]},"o":{"x":[0.167],"y":[0.167]},"t":1270,"s":[356]},{"t":1297,"s":[715]}]},"p":{"a":0,"k":[2754.5,1158,0]},"a":{"a":0,"k":[100,100,0]},"s":{"a":0,"k":[46.451,46.451,100]}},"ao":0,"hasMask":true,"masksProperties":[{"inv":false,"mode":"a","pt":{"a":0,"k":{"i":[[36.183,0],[0,-36.183],[-36.183,0],[0,36.183]],"o":[[-36.183,0],[0,36.183],[36.183,0],[0,-36.183]],"v":[[93.529,30],[28.014,95.514],[93.529,161.029],[159.043,95.514]],"c":true}},"o":{"a":0,"k":100},"x":{"a":0,"k":0},"nm":"Mask 1"}],"ef":[{"ty":22,"nm":"Stroke","np":13,"mn":"ADBE Stroke","ix":1,"en":1,"ef":[{"ty":10,"nm":"Path","mn":"ADBE Stroke-0001","ix":1,"v":{"a":0,"k":1}},{"ty":7,"nm":"All Masks","mn":"ADBE Stroke-0010","ix":2,"v":{"a":0,"k":0}},{"ty":7,"nm":"Stroke Sequentially","mn":"ADBE Stroke-0011","ix":3,"v":{"a":0,"k":1}},{"ty":2,"nm":"Color","mn":"ADBE Stroke-0002","ix":4,"v":{"a":0,"k":[1,1,1,1]}},{"ty":0,"nm":"Brush Size","mn":"ADBE Stroke-0003","ix":5,"v":{"a":0,"k":4.6}},{"ty":0,"nm":"Brush Hardness","mn":"ADBE Stroke-0004","ix":6,"v":{"a":0,"k":0.75}},{"ty":0,"nm":"Opacity","mn":"ADBE Stroke-0005","ix":7,"v":{"a":0,"k":1}},{"ty":0,"nm":"Start","mn":"ADBE Stroke-0008","ix":8,"v":{"a":0,"k":0}},{"ty":0,"nm":"End","mn":"ADBE Stroke-0009","ix":9,"v":{"a":1,"k":[{"i":{"x":[0.833],"y":[0.833]},"o":{"x":[0.167],"y":[0.167]},"t":1270,"s":[8]},{"t":1297,"s":[90]}]}},{"ty":7,"nm":"Spacing","mn":"ADBE Stroke-0006","ix":10,"v":{"a":0,"k":15}},{"ty":7,"nm":"Paint Style","mn":"ADBE Stroke-0007","ix":11,"v":{"a":0,"k":2}}]}],"sw":200,"sh":200,"sc":"#2d2d2d","ip":1270,"op":1298,"st":546,"bm":0},{"ddd":0,"ind":31,"ty":1,"nm":"throbber 5","sr":1,"ks":{"r":{"a":1,"k":[{"i":{"x":[0.833],"y":[0.833]},"o":{"x":[0.167],"y":[0.167]},"t":1298,"s":[356]},{"t":1325,"s":[715]}]},"p":{"a":0,"k":[2754.5,1158,0]},"a":{"a":0,"k":[100,100,0]},"s":{"a":0,"k":[46.451,46.451,100]}},"ao":0,"hasMask":true,"masksProperties":[{"inv":false,"mode":"a","pt":{"a":0,"k":{"i":[[36.183,0],[0,-36.183],[-36.183,0],[0,36.183]],"o":[[-36.183,0],[0,36.183],[36.183,0],[0,-36.183]],"v":[[93.529,30],[28.014,95.514],[93.529,161.029],[159.043,95.514]],"c":true}},"o":{"a":0,"k":100},"x":{"a":0,"k":0},"nm":"Mask 1"}],"ef":[{"ty":22,"nm":"Stroke","np":13,"mn":"ADBE Stroke","ix":1,"en":1,"ef":[{"ty":10,"nm":"Path","mn":"ADBE Stroke-0001","ix":1,"v":{"a":0,"k":1}},{"ty":7,"nm":"All Masks","mn":"ADBE Stroke-0010","ix":2,"v":{"a":0,"k":0}},{"ty":7,"nm":"Stroke Sequentially","mn":"ADBE Stroke-0011","ix":3,"v":{"a":0,"k":1}},{"ty":2,"nm":"Color","mn":"ADBE Stroke-0002","ix":4,"v":{"a":0,"k":[1,1,1,1]}},{"ty":0,"nm":"Brush Size","mn":"ADBE Stroke-0003","ix":5,"v":{"a":0,"k":4.6}},{"ty":0,"nm":"Brush Hardness","mn":"ADBE Stroke-0004","ix":6,"v":{"a":0,"k":0.75}},{"ty":0,"nm":"Opacity","mn":"ADBE Stroke-0005","ix":7,"v":{"a":0,"k":1}},{"ty":0,"nm":"Start","mn":"ADBE Stroke-0008","ix":8,"v":{"a":0,"k":0}},{"ty":0,"nm":"End","mn":"ADBE Stroke-0009","ix":9,"v":{"a":1,"k":[{"i":{"x":[0.833],"y":[0.833]},"o":{"x":[0.167],"y":[0.167]},"t":1298,"s":[8]},{"t":1325,"s":[90]}]}},{"ty":7,"nm":"Spacing","mn":"ADBE Stroke-0006","ix":10,"v":{"a":0,"k":15}},{"ty":7,"nm":"Paint Style","mn":"ADBE Stroke-0007","ix":11,"v":{"a":0,"k":2}}]}],"sw":200,"sh":200,"sc":"#2d2d2d","ip":1298,"op":1326,"st":574,"bm":0},{"ddd":0,"ind":32,"ty":1,"nm":"throbber 2","sr":1,"ks":{"o":{"a":1,"k":[{"i":{"x":[0.833],"y":[0.833]},"o":{"x":[0.167],"y":[0.167]},"t":1336,"s":[100]},{"t":1349,"s":[0]}]},"r":{"a":1,"k":[{"i":{"x":[0.833],"y":[0.833]},"o":{"x":[0.167],"y":[0.167]},"t":1326,"s":[356]},{"t":1353,"s":[715]}]},"p":{"a":0,"k":[2754.5,1158,0]},"a":{"a":0,"k":[100,100,0]},"s":{"a":0,"k":[46.451,46.451,100]}},"ao":0,"hasMask":true,"masksProperties":[{"inv":false,"mode":"a","pt":{"a":0,"k":{"i":[[36.183,0],[0,-36.183],[-36.183,0],[0,36.183]],"o":[[-36.183,0],[0,36.183],[36.183,0],[0,-36.183]],"v":[[93.529,30],[28.014,95.514],[93.529,161.029],[159.043,95.514]],"c":true}},"o":{"a":0,"k":100},"x":{"a":0,"k":0},"nm":"Mask 1"}],"ef":[{"ty":22,"nm":"Stroke","np":13,"mn":"ADBE Stroke","ix":1,"en":1,"ef":[{"ty":10,"nm":"Path","mn":"ADBE Stroke-0001","ix":1,"v":{"a":0,"k":1}},{"ty":7,"nm":"All Masks","mn":"ADBE Stroke-0010","ix":2,"v":{"a":0,"k":0}},{"ty":7,"nm":"Stroke Sequentially","mn":"ADBE Stroke-0011","ix":3,"v":{"a":0,"k":1}},{"ty":2,"nm":"Color","mn":"ADBE Stroke-0002","ix":4,"v":{"a":0,"k":[1,1,1,1]}},{"ty":0,"nm":"Brush Size","mn":"ADBE Stroke-0003","ix":5,"v":{"a":0,"k":4.6}},{"ty":0,"nm":"Brush Hardness","mn":"ADBE Stroke-0004","ix":6,"v":{"a":0,"k":0.75}},{"ty":0,"nm":"Opacity","mn":"ADBE Stroke-0005","ix":7,"v":{"a":0,"k":1}},{"ty":0,"nm":"Start","mn":"ADBE Stroke-0008","ix":8,"v":{"a":0,"k":0}},{"ty":0,"nm":"End","mn":"ADBE Stroke-0009","ix":9,"v":{"a":1,"k":[{"i":{"x":[0.833],"y":[0.833]},"o":{"x":[0.167],"y":[0.167]},"t":1326,"s":[8]},{"t":1353,"s":[90]}]}},{"ty":7,"nm":"Spacing","mn":"ADBE Stroke-0006","ix":10,"v":{"a":0,"k":15}},{"ty":7,"nm":"Paint Style","mn":"ADBE Stroke-0007","ix":11,"v":{"a":0,"k":2}}]}],"sw":200,"sh":200,"sc":"#2d2d2d","ip":1326,"op":1350,"st":602,"bm":0},{"ddd":0,"ind":33,"ty":0,"nm":"posts + video","refId":"comp_1","sr":1,"ks":{"o":{"a":1,"k":[{"i":{"x":[0.833],"y":[0.833]},"o":{"x":[0.167],"y":[0.167]},"t":1336,"s":[100]},{"t":1349,"s":[0]}]},"p":{"a":0,"k":[2186.5,1226,0]},"a":{"a":0,"k":[2186.5,1367.5,0]}},"ao":0,"hasMask":true,"masksProperties":[{"inv":false,"mode":"a","pt":{"a":0,"k":{"i":[[0,0],[0,0],[0,0],[0,0]],"o":[[0,0],[0,0],[0,0],[0,0]],"v":[[3340.531,1077],[2490.5,1049],[2466.5,1427.984],[3340.531,1535.984]],"c":true}},"o":{"a":0,"k":100},"x":{"a":0,"k":0},"nm":"Mask 1"}],"w":4373,"h":2735,"ip":952,"op":1350,"st":952,"bm":0},{"ddd":0,"ind":34,"ty":2,"nm":"bg","refId":"image_31","sr":1,"ks":{"o":{"a":1,"k":[{"i":{"x":[0.833],"y":[0.833]},"o":{"x":[0.167],"y":[0.167]},"t":947,"s":[0]},{"i":{"x":[0.833],"y":[0.833]},"o":{"x":[0.167],"y":[0.167]},"t":953,"s":[100]},{"i":{"x":[0.833],"y":[0.833]},"o":{"x":[0.167],"y":[0.167]},"t":1336,"s":[100]},{"i":{"x":[0.833],"y":[0.833]},"o":{"x":[0.167],"y":[0.167]},"t":1349,"s":[0]},{"i":{"x":[0.833],"y":[0.833]},"o":{"x":[0.167],"y":[0.167]},"t":1477,"s":[100]},{"t":1490,"s":[0]}]},"p":{"a":0,"k":[2906.5,1083.5,0]},"a":{"a":0,"k":[484.5,327.5,0]}},"ao":0,"ip":947,"op":1350,"st":947,"bm":0},{"ddd":0,"ind":35,"ty":2,"nm":"BACKGROUND","refId":"image_32","sr":1,"ks":{"p":{"a":0,"k":[2148,1266.5,0]},"a":{"a":0,"k":[1950,1124.5,0]}},"ao":0,"ef":[{"ty":5,"nm":"Corner Pin","np":6,"mn":"ADBE Corner Pin","ix":1,"en":1,"ef":[{"ty":3,"nm":"Upper Left","mn":"ADBE Corner Pin-0001","ix":1,"v":{"a":0,"k":[0,0]}},{"ty":3,"nm":"Upper Right","mn":"ADBE Corner Pin-0002","ix":2,"v":{"a":0,"k":[3900,0]}},{"ty":3,"nm":"Lower Left","mn":"ADBE Corner Pin-0003","ix":3,"v":{"a":0,"k":[0,2249]}},{"ty":3,"nm":"Lower Right","mn":"ADBE Corner Pin-0004","ix":4,"v":{"a":0,"k":[3900,2249]}}]},{"ty":5,"nm":"Corner Pin 2","np":6,"mn":"ADBE Corner Pin","ix":2,"en":1,"ef":[{"ty":3,"nm":"Upper Left","mn":"ADBE Corner Pin-0001","ix":1,"v":{"a":0,"k":[0,0]}},{"ty":3,"nm":"Upper Right","mn":"ADBE Corner Pin-0002","ix":2,"v":{"a":0,"k":[3900,0]}},{"ty":3,"nm":"Lower Left","mn":"ADBE Corner Pin-0003","ix":3,"v":{"a":0,"k":[0,2249]}},{"ty":3,"nm":"Lower Right","mn":"ADBE Corner Pin-0004","ix":4,"v":{"a":0,"k":[3900,2249]}}]},{"ty":5,"nm":"Corner Pin 3","np":6,"mn":"ADBE Corner Pin","ix":3,"en":1,"ef":[{"ty":3,"nm":"Upper Left","mn":"ADBE Corner Pin-0001","ix":1,"v":{"a":0,"k":[0,0]}},{"ty":3,"nm":"Upper Right","mn":"ADBE Corner Pin-0002","ix":2,"v":{"a":0,"k":[3900,0]}},{"ty":3,"nm":"Lower Left","mn":"ADBE Corner Pin-0003","ix":3,"v":{"a":0,"k":[0,2249]}},{"ty":3,"nm":"Lower Right","mn":"ADBE Corner Pin-0004","ix":4,"v":{"a":0,"k":[3900,2249]}}]},{"ty":5,"nm":"Corner Pin 4","np":6,"mn":"ADBE Corner Pin","ix":4,"en":1,"ef":[{"ty":3,"nm":"Upper Left","mn":"ADBE Corner Pin-0001","ix":1,"v":{"a":0,"k":[0,0]}},{"ty":3,"nm":"Upper Right","mn":"ADBE Corner Pin-0002","ix":2,"v":{"a":0,"k":[3900,0]}},{"ty":3,"nm":"Lower Left","mn":"ADBE Corner Pin-0003","ix":3,"v":{"a":0,"k":[0,2249]}},{"ty":3,"nm":"Lower Right","mn":"ADBE Corner Pin-0004","ix":4,"v":{"a":0,"k":[3900,2249]}}]},{"ty":5,"nm":"Corner Pin 5","np":6,"mn":"ADBE Corner Pin","ix":5,"en":1,"ef":[{"ty":3,"nm":"Upper Left","mn":"ADBE Corner Pin-0001","ix":1,"v":{"a":0,"k":[0,0]}},{"ty":3,"nm":"Upper Right","mn":"ADBE Corner Pin-0002","ix":2,"v":{"a":0,"k":[3900,0]}},{"ty":3,"nm":"Lower Left","mn":"ADBE Corner Pin-0003","ix":3,"v":{"a":0,"k":[0,2249]}},{"ty":3,"nm":"Lower Right","mn":"ADBE Corner Pin-0004","ix":4,"v":{"a":0,"k":[3900,2249]}}]},{"ty":5,"nm":"Corner Pin 6","np":6,"mn":"ADBE Corner Pin","ix":6,"en":1,"ef":[{"ty":3,"nm":"Upper Left","mn":"ADBE Corner Pin-0001","ix":1,"v":{"a":0,"k":[0,0]}},{"ty":3,"nm":"Upper Right","mn":"ADBE Corner Pin-0002","ix":2,"v":{"a":0,"k":[3900,0]}},{"ty":3,"nm":"Lower Left","mn":"ADBE Corner Pin-0003","ix":3,"v":{"a":0,"k":[0,2249]}},{"ty":3,"nm":"Lower Right","mn":"ADBE Corner Pin-0004","ix":4,"v":{"a":0,"k":[3900,2249]}}]}],"ip":0,"op":1350,"st":-196,"bm":0}],"markers":[]}
